{
  

    "blog-2016-04-19-hello-world": {
      "title": "Hello World",
      "content"	 : "Table of Contents  Table of Contents  Basic Functionality          Headers        Header 1          Header 2                  Header 3                    Styling      Lists      Links      Images      Code      MathJax      Tables      Quotes      Rule      HTML        Advanced Functionality          Color and Alignment      Basic FunctionalityHeadersHeader 1Header 2Header 3StylingBoldItalicsBold and ItalicsLists      Item 1        Item 2        Unordered Item                  Sub Item 1                  Bold Sub Sub Ordered Item                    LinksIn-LineI’m a reference-style link 1I’m a reference-style link 1ImagesHold your pointer clicked over the image to expand the view.CodeInline code.import numpy as npdef hello_world():    print(&#39;Hello World!&#39;&#39;)MathJaxUse MathJax for Math.Tables            Here      is      a      row!                  is      Left      Center      Right              a      cut      it      A              column      short      B      C      Quotes  War does not decide who is right, only who is left.RuleHTMLCan write the whole post or sections in HTML for very specific needs. [For the advanced user or the code savvy.]Advanced FunctionalityHead over to the documentation page for tutorials on some basic html formatting and some extensions you can use for cool stuff like interactive 3D visualizations.Color and AlignmentThis text is centered.This is a red text with blue and green inline text.",
      "url": "/mysite/blog/2016/04/19/Hello-World/",
      "author": "Nitin Prakash",
      "categories": "Blog"
    }
    
  

  
    
  
    
  
    
  
    
  
    
  
    
  
    
  
    
  
    
  
    
  
    
  
    
  
}